{
  "parent": "minecraft:story/mine_stone",
  "display": {
    "icon": {
      "item": "earlygame:copper_ingot"
    },
    "title": {
      "translate": "advancements.story.smelt_copper.title"
    },
    "description": {
      "translate": "advancements.story.smelt_copper.description"
    },
    "frame": "task",
    "show_toast": true,
    "announce_to_chat": true,
    "hidden": false
  },
  "criteria": {
    "copper": {
      "trigger": "minecraft:inventory_changed",
      "conditions": {
        "items": [
          {
            "item": "earlygame:copper_ingot"
          }
        ]
      }
    }
  },
  "requirements": [
    [
      "copper"
    ]
  ]
}