{
    "schemaVersion": 1,
    "id": "earlygame",
    "version": "1.17.x-1.1.1",

    "name": "EarlyGame",
    "description": "A Fabric mod that focuses on changing early game progression that makes the gameplay feel more \"realistic\".",
    "authors": [
        "JayCeeCreates"
    ],
    "contact": {
        "homepage": "https://www.curseforge.com/minecraft/mc-mods/earlygame",
        "sources": "https://github.com/JayCeeCreates/earlygame",
        "issues": "https://github.com/JayCeeCreates/earlygame/issues"
    },

    "license": "MIT",
    "icon": "assets/earlygame/icon.png",
  
    "environment": "*",
    "entrypoints": {
        "main": [
            "jayceecreates.earlygame.EarlyGame"
        ],
        "client": [
            "jayceecreates.earlygame.EarlyGameClient"
        ],
        "modmenu": [
            "jayceecreates.earlygame.config.ModMenuIntegration"
        ]
    },
    "mixins": [
        "earlygame.mixins.json"
    ],
    "accessWidener" : "earlygame.accesswidener",
  
    "depends": {
        "fabricloader": ">=0.11.3",
        "fabric": "*",
        "minecraft": "1.17.x",
        "java": ">=16"
    }
}
